LICENSE.txt
README.md
setup.cfg
setup.py
Why_XAI.egg-info/PKG-INFO
Why_XAI.egg-info/SOURCES.txt
Why_XAI.egg-info/dependency_links.txt
Why_XAI.egg-info/requires.txt
Why_XAI.egg-info/top_level.txt
why/__init__.py
why/explain/__init__.py
why/explain/explain.py
why/explain/explain_utils/__init__.py
why/explain/explain_utils/image.py
why/explain/pytorch/__init__.py
why/explain/pytorch/gradcam.py
why/explain/pytorch/gradcamplusplus.py
why/explain/pytorch/utils.py
why/explain/tensorflow/__init__.py
why/explain/tensorflow/gradcam.py
why/explain/tensorflow/gradcamplusplus.py
why/explain/tensorflow/utils.py