Metadata-Version: 2.1
Name: Why-XAI
Version: 0.1.0
Summary: Framework-agnostic CNN XAI Library
Home-page: https://github.com/mburaksayici
Author: Mehmet Burak Sayıcı
Author-email: mburaksayici@gmail.com
License: BSD 2-clause
Classifier: Development Status :: 1 - Planning
Classifier: Intended Audience :: Science/Research
Classifier: License :: OSI Approved :: BSD License
Classifier: Operating System :: POSIX :: Linux
Classifier: Programming Language :: Python :: 3.7
Classifier: Programming Language :: Python :: 3.8
License-File: LICENSE.txt
